CHANGELOG.rst
LICENSE
MANIFEST.in
README.rst
VERSION
setup.py
tosixinch/__init__.py
tosixinch/_lxml_html.py
tosixinch/action.py
tosixinch/clean.py
tosixinch/configfetch.py
tosixinch/content.py
tosixinch/convert.py
tosixinch/dispatch.py
tosixinch/download.py
tosixinch/extract.py
tosixinch/imagesize.py
tosixinch/inspect.py
tosixinch/location.py
tosixinch/lxml_html.py
tosixinch/main.py
tosixinch/manuopen.py
tosixinch/settings.py
tosixinch/stylesheet.py
tosixinch/system.py
tosixinch/templite.py
tosixinch/textformat.py
tosixinch/toc.py
tosixinch/urlmap.py
tosixinch/urlno.py
tosixinch/zconfigparser.py
tosixinch.egg-info/PKG-INFO
tosixinch.egg-info/SOURCES.txt
tosixinch.egg-info/dependency_links.txt
tosixinch.egg-info/entry_points.txt
tosixinch.egg-info/not-zip-safe
tosixinch.egg-info/requires.txt
tosixinch.egg-info/top_level.txt
tosixinch/data/_tosixinch.bash
tosixinch/data/pcode.ini
tosixinch/data/rsrcs.txt
tosixinch/data/site.ini
tosixinch/data/site.sample.ini
tosixinch/data/tosixinch.ini
tosixinch/data/css/sample.t.css
tosixinch/data/fini/_site.fini
tosixinch/data/fini/_tosixinch.fini
tosixinch/process/inspect_sample.py
tosixinch/process/sample.py
tosixinch/script/_man.py
tosixinch/script/_pcode.py
tosixinch/script/_viewer.py
tosixinch/script/pcode/_ctags.py
tosixinch/script/pcode/_ftype.py
tosixinch/script/pcode/_ftype_base.py
tosixinch/script/pcode/_pygments.py
tosixinch/script/pcode/python.py