Metadata-Version: 2.1
Name: tosixinch
Version: 0.9.0
Summary: Browser to e-reader in a few minutes
Home-page: https://github.com/openandclose/tosixinch
Author: Open Close
Author-email: openandclose23@gmail.com
License: MIT
Keywords: html pdf lxml extraction conversion e-reader kindle kobo
Platform: UNKNOWN
Classifier: Development Status :: 3 - Alpha
Classifier: Intended Audience :: End Users/Desktop
Classifier: License :: OSI Approved :: MIT License
Classifier: Programming Language :: Python :: 3 :: Only
Classifier: Programming Language :: Python :: 3.6
Classifier: Programming Language :: Python :: 3.7
Classifier: Programming Language :: Python :: 3.8
Classifier: Programming Language :: Python :: 3.9
Classifier: Programming Language :: Python :: 3.10
Classifier: Topic :: Text Processing :: Markup :: HTML
Classifier: Topic :: Utilities
Requires-Python: ~=3.6
Provides-Extra: test
Provides-Extra: dev
License-File: LICENSE
